{
	"providerName": "University of Notre Dame",
	"language": "en-US",
	"lastUpdated": "2019-07-02T09:00:01",
	"shortFormVideos": [{
		"id": "345513455",
		"title": "Freshman Football Highlight Video",
		"content": {
			"dateAdded": "2019-07-01T16:34:03+00:00",
			"videos": [{
				"url": "https://gcs-vimeo.akamaized.net/exp=1562612455~acl=%2A%2F1388014491.mp4%2A~hmac=617a6cf1a40cf712f8a880e5862ffaaf50c8af29e809c0b19115fe31f7cf2cf2/vimeo-prod-skyfire-std-us/01/4102/13/345513455/1388014491.mp4",
				"quality": "SD",
				"videoType": "mp4",
				"bitrate": "1328"
			}],
			"duration": 926,
			"captions": {
				"url": "",
				"Language": "en",
				"captionType": ""
			}
		},
		"thumbnail": "https://i.vimeocdn.com/video/795306898_1280x720.jpg",
		"shortDescription": "A highlight video from my freshman Year at John Adams Highschool.",
		"releaseDate": "2019-07-01T16:34:03+00:00",
		"tags": "sports"
	}],
	"categories": [{
		"name": "Football",
		"playlistName": "football",
		"order": "most_recent"
	}],
	"playlists": [{
		"name": "football",
		"itemIds": ["345513455"]
	}]
}
